{
  "meta": {
    "language": "de",
    "version": "1.0",
    "level": "B1",
    "source": "MEB Almanca Öğretim Programı 2018"
  },
  "categories": [
    {
      "id": "emotionen",
      "name": "Emotionen",
      "icon": "🎭",
      "description": "Öğrenciler; neden-sonuç ve zıtlık bildiren bağlaçları kullanarak hem kendi duygularını hem de başkalarının ruh hallerini, dilbilgisi kurallarına uygun ve mantıksal bir çerçevede ifade etme becerisi kazanırlar.",
      "questions": [
        {
          "id": "emo_001",
          "type": "multiple_choice",
          "text": "Ich mag keine Horrorfilme...",
          "sound": "emo_001.mp3",
          "soundText": "Ich mag keine Horrorfilme...",
          "options": [
            "aber Komödien.",
            "sondern Komödien.",
            "obwohl Komödien.",
            "weil Komödien."
          ],
          "answer": 1,
          "duration": 40
        },
        {
          "id": "emo_002",
          "type": "multiple_choice",
          "text": "Ich gehe selten ins Kino...",
          "sound": "emo_002.mp3",
          "soundText": "Ich gehe selten ins Kino...",
          "options": [
            "obwohl ich Filme liebe.",
            "weil ich Filme liebe.",
            "sondern ich Filme liebe.",
            "deshalb ich Filme liebe."
          ],
          "answer": 0,
          "duration": 40
        },
        {
          "id": "emo_003",
          "type": "multiple_choice",
          "text": "Er war sehr erschrocken...",
          "sound": "emo_003.mp3",
          "soundText": "Er war sehr erschrocken...",
          "options": [
            "obwohl er mutig ist.",
            "deshalb er mutig ist.",
            "sondern er mutig ist.",
            "weil er mutig ist."
          ],
          "answer": 0,
          "duration": 40
        },
        {
          "id": "emo_004",
          "type": "multiple_choice",
          "text": "Die Situation war peinlich...",
          "sound": "emo_004.mp3",
          "soundText": "Die Situation war peinlich...",
          "options": [
            "trotzdem lachten alle.",
            "obwohl lachten alle.",
            "sondern lachten alle.",
            "weil lachten alle."
          ],
          "answer": 0,
          "duration": 40
        },
        {
          "id": "emo_005",
          "type": "multiple_choice",
          "text": "Aylin ist traurig...",
          "sound": "emo_005.mp3",
          "soundText": "Aylin ist traurig...",
          "options": [
            "sondern sie weint.",
            "trotzdem lacht sie.",
            "obwohl sie lacht.",
            "weil sie lacht."
          ],
          "answer": 1,
          "duration": 40
        },
        {
          "id": "emo_006",
          "type": "multiple_choice",
          "text": "Der Film war langweilig...",
          "sound": "emo_006.mp3",
          "soundText": "Der Film war langweilig...",
          "options": [
            "obwohl alle ihn sahen.",
            "sondern alle ihn sahen.",
            "weil alle ihn sahen.",
            "trotzdem sahen ihn alle."
          ],
          "answer": 3,
          "duration": 40
        },
        {
          "id": "emo_007",
          "type": "multiple_choice",
          "text": "Klaus war wütend...",
          "sound": "emo_007.mp3",
          "soundText": "Klaus war wütend...",
          "options": [
            "sondern er ruhig blieb.",
            "obwohl er ruhig blieb.",
            "weil er ruhig blieb.",
            "deshalb er ruhig blieb."
          ],
          "answer": 1,
          "duration": 40
        },
        {
          "id": "emo_008",
          "type": "multiple_choice",
          "text": "Ich bin glücklich...",
          "sound": "emo_008.mp3",
          "soundText": "Ich bin glücklich...",
          "options": [
            "sondern du traurig bist.",
            "obwohl du traurig bist.",
            "weil du traurig bist.",
            "trotzdem du traurig bist."
          ],
          "answer": 1,
          "duration": 40
        },
        {
          "id": "emo_009",
          "type": "multiple_choice",
          "text": "Sie lacht...",
          "sound": "emo_009.mp3",
          "soundText": "Sie lacht...",
          "options": [
            "obwohl sie traurig ist.",
            "weil sie traurig ist.",
            "sondern sie traurig ist.",
            "deshalb sie traurig ist."
          ],
          "answer": 0,
          "duration": 40
        },
        {
          "id": "emo_010",
          "type": "multiple_choice",
          "text": "Er ist überrascht...",
          "sound": "emo_010.mp3",
          "soundText": "Er ist überrascht...",
          "options": [
            "weil er es wusste.",
            "sondern er es wusste.",
            "obwohl er es wusste.",
            "trotzdem er es wusste."
          ],
          "answer": 2,
          "duration": 40
        },
        {
          "id": "emo_011",
          "type": "multiple_choice",
          "text": "Anna weint...",
          "sound": "emo_011.mp3",
          "soundText": "Anna weint...",
          "options": [
            "obwohl sie glücklich ist.",
            "weil sie glücklich ist.",
            "trotzdem sie glücklich ist.",
            "deshalb ist sie glücklich."
          ],
          "answer": 0,
          "duration": 40
        },
        {
          "id": "emo_012",
          "type": "multiple_choice",
          "text": "Er schreit laut...",
          "sound": "emo_012.mp3",
          "soundText": "Er schreit laut...",
          "options": [
            "obwohl er ruhig ist.",
            "sondern er ruhig ist.",
            "trotzdem er ruhig ist.",
            "weil er ruhig ist."
          ],
          "answer": 0,
          "duration": 40
        },
        {
          "id": "emo_013",
          "type": "multiple_choice",
          "text": "Sie ist nicht traurig...",
          "sound": "emo_013.mp3",
          "soundText": "Sie ist nicht traurig...",
          "options": [
            "obwohl glücklich.",
            "sondern glücklich.",
            "trotzdem glücklich.",
            "weil glücklich."
          ],
          "answer": 1,
          "duration": 40
        },
        {
          "id": "emo_014",
          "type": "multiple_choice",
          "text": "Das Konzert war wunderschön...",
          "sound": "emo_014.mp3",
          "soundText": "Das Konzert war wunderschön...",
          "options": [
            "sondern alle weinten vor Freude.",
            "weil alle weinten vor Freude.",
            "trotzdem weinten alle vor Freude.",
            "obwohl alle weinten vor Freude."
          ],
          "answer": 2,
          "duration": 40
        },
        {
          "id": "emo_015",
          "type": "multiple_choice",
          "text": "Ich bin nicht wütend...",
          "sound": "emo_015.mp3",
          "soundText": "Ich bin nicht wütend...",
          "options": [
            "trotzdem enttäuscht.",
            "weil enttäuscht.",
            "sondern enttäuscht.",
            "obwohl enttäuscht."
          ],
          "answer": 2,
          "duration": 40
        },
        {
          "id": "emo_016",
          "type": "multiple_choice",
          "text": "Er lächelt immer...",
          "sound": "emo_016.mp3",
          "soundText": "Er lächelt immer...",
          "options": [
            "weil er Probleme hat.",
            "sondern er Probleme hat.",
            "deshalb hat er Probleme.",
            "obwohl er Probleme hat."
          ],
          "answer": 3,
          "duration": 40
        },
        {
          "id": "emo_017",
          "type": "multiple_choice",
          "text": "Das Kind ist ängstlich...",
          "sound": "emo_017.mp3",
          "soundText": "Das Kind ist ängstlich...",
          "options": [
            "trotzdem geht es allein raus.",
            "obwohl geht es allein raus.",
            "weil geht es allein raus.",
            "deshalb geht es allein raus."
          ],
          "answer": 0,
          "duration": 40
        },
        {
          "id": "emo_018",
          "type": "multiple_choice",
          "text": "Sie ist erschöpft...",
          "sound": "emo_018.mp3",
          "soundText": "Sie ist erschöpft...",
          "options": [
            "obwohl sie weiterarbeitet.",
            "sondern sie weiterarbeitet.",
            "trotzdem sie weiterarbeitet.",
            "deshalb arbeitet sie weiter."
          ],
          "answer": 0,
          "duration": 40
        },
        {
          "id": "emo_019",
          "type": "multiple_choice",
          "text": "Er ist stolz...",
          "sound": "emo_019.mp3",
          "soundText": "Er ist stolz...",
          "options": [
            "trotzdem er gewonnen hat.",
            "obwohl er gewonnen hat.",
            "weil er gewonnen hat.",
            "sondern er gewonnen hat."
          ],
          "answer": 2,
          "duration": 40
        },
        {
          "id": "emo_020",
          "type": "multiple_choice",
          "text": "Sie fühlt sich einsam...",
          "sound": "emo_020.mp3",
          "soundText": "Sie fühlt sich einsam...",
          "options": [
            "weil viele Freunde da sind.",
            "deshalb sind viele Freunde da.",
            "sondern viele Freunde da sind.",
            "obwohl viele Freunde da sind."
          ],
          "answer": 3,
          "duration": 40
        },
        {
          "id": "emo_021",
          "type": "multiple_choice",
          "text": "Ich bin heute sehr glücklich, ___",
          "sound": "emo_021.mp3",
          "soundText": "Ich bin heute sehr glücklich, ___",
          "options": [
            "weil ich eine gute Note bekommen habe.",
            "sondern ich eine gute Note bekommen habe.",
            "obwohl ich eine gute Note bekommen habe.",
            "trotzdem ich eine gute Note bekommen habe."
          ],
          "answer": 0,
          "duration": 40
        },
        {
          "id": "emo_022",
          "type": "multiple_choice",
          "text": "Sie lacht laut, ___",
          "sound": "emo_022.mp3",
          "soundText": "Sie lacht laut, ___",
          "options": [
            "weil sie sehr traurig ist.",
            "aber sie sehr traurig ist.",
            "obwohl sie sehr traurig ist.",
            "sondern sie sehr traurig ist."
          ],
          "answer": 2,
          "duration": 40
        },
        {
          "id": "emo_023",
          "type": "multiple_choice",
          "text": "Er ist wütend, ___",
          "sound": "emo_023.mp3",
          "soundText": "Er ist wütend, ___",
          "options": [
            "aber er bleibt ruhig.",
            "weil er bleibt ruhig.",
            "sondern er bleibt ruhig.",
            "obwohl er bleibt ruhig."
          ],
          "answer": 0,
          "duration": 40
        },
        {
          "id": "emo_024",
          "type": "multiple_choice",
          "text": "Ich bin nicht ängstlich, ___",
          "sound": "emo_024.mp3",
          "soundText": "Ich bin nicht ängstlich, ___",
          "options": [
            "weil aufgeregt.",
            "aber aufgeregt.",
            "obwohl aufgeregt.",
            "sondern aufgeregt."
          ],
          "answer": 3,
          "duration": 40
        },
        {
          "id": "emo_025",
          "type": "multiple_choice",
          "text": "Sie ist sehr nervös. ___",
          "sound": "emo_025.mp3",
          "soundText": "Sie ist sehr nervös. ___",
          "options": [
            "Weil hält sie die Präsentation gut.",
            "Obwohl hält sie die Präsentation gut.",
            "Trotzdem hält sie die Präsentation gut.",
            "Sondern hält sie die Präsentation gut."
          ],
          "answer": 2,
          "duration": 40
        },
        {
          "id": "emo_026",
          "type": "multiple_choice",
          "text": "Er weint, ___",
          "sound": "emo_026.mp3",
          "soundText": "Er weint, ___",
          "options": [
            "aber sein Hund gestorben ist.",
            "sondern sein Hund gestorben ist.",
            "weil sein Hund gestorben ist.",
            "trotzdem sein Hund gestorben ist."
          ],
          "answer": 2,
          "duration": 40
        },
        {
          "id": "emo_027",
          "type": "multiple_choice",
          "text": "Ich bin eifersüchtig, ___",
          "sound": "emo_027.mp3",
          "soundText": "Ich bin eifersüchtig, ___",
          "options": [
            "obwohl ich es nicht zugeben möchte.",
            "weil ich es nicht zugeben möchte.",
            "sondern ich es nicht zugeben möchte.",
            "aber ich es nicht zugeben möchte."
          ],
          "answer": 0,
          "duration": 40
        },
        {
          "id": "emo_028",
          "type": "multiple_choice",
          "text": "Sie ist enttäuscht, ___",
          "sound": "emo_028.mp3",
          "soundText": "Sie ist enttäuscht, ___",
          "options": [
            "weil sie gibt nicht auf.",
            "aber sie gibt nicht auf.",
            "sondern sie gibt nicht auf.",
            "obwohl sie gibt nicht auf."
          ],
          "answer": 1,
          "duration": 40
        },
        {
          "id": "emo_029",
          "type": "multiple_choice",
          "text": "Das Kind ist nicht traurig, ___",
          "sound": "emo_029.mp3",
          "soundText": "Das Kind ist nicht traurig, ___",
          "options": [
            "weil es einsam ist.",
            "obwohl es einsam ist.",
            "sondern einsam.",
            "trotzdem es einsam ist."
          ],
          "answer": 2,
          "duration": 40
        },
        {
          "id": "emo_030",
          "type": "multiple_choice",
          "text": "Sie hat Angst vor Hunden. ___",
          "sound": "emo_030.mp3",
          "soundText": "Sie hat Angst vor Hunden. ___",
          "options": [
            "Weil streichelt sie den Hund.",
            "Trotzdem streichelt sie den Hund.",
            "Sondern streichelt sie den Hund.",
            "Obwohl streichelt sie den Hund."
          ],
          "answer": 1,
          "duration": 40
        },
        {
          "id": "emo_031",
          "type": "multiple_choice",
          "text": "Ich fühle mich einsam, ___",
          "sound": "emo_031.mp3",
          "soundText": "Ich fühle mich einsam, ___",
          "options": [
            "aber meine Freunde nicht da sind.",
            "weil meine Freunde nicht da sind.",
            "sondern meine Freunde nicht da sind.",
            "trotzdem meine Freunde nicht da sind."
          ],
          "answer": 1,
          "duration": 40
        },
        {
          "id": "emo_032",
          "type": "multiple_choice",
          "text": "Er ist stolz, ___",
          "sound": "emo_032.mp3",
          "soundText": "Er ist stolz, ___",
          "options": [
            "weil er den Wettkampf verloren hat.",
            "aber er den Wettkampf verloren hat.",
            "obwohl er den Wettkampf verloren hat.",
            "sondern er den Wettkampf verloren hat."
          ],
          "answer": 2,
          "duration": 40
        },
        {
          "id": "emo_033",
          "type": "multiple_choice",
          "text": "Sie liebt ihn sehr, ___",
          "sound": "emo_033.mp3",
          "soundText": "Sie liebt ihn sehr, ___",
          "options": [
            "aber sie ist eifersüchtig auf ihn.",
            "weil sie ist eifersüchtig auf ihn.",
            "sondern sie ist eifersüchtig auf ihn.",
            "obwohl sie ist eifersüchtig auf ihn."
          ],
          "answer": 0,
          "duration": 40
        },
        {
          "id": "emo_034",
          "type": "multiple_choice",
          "text": "Ich bin nicht entspannt, ___",
          "sound": "emo_034.mp3",
          "soundText": "Ich bin nicht entspannt, ___",
          "options": [
            "weil gestresst.",
            "obwohl gestresst.",
            "aber gestresst.",
            "sondern gestresst."
          ],
          "answer": 3,
          "duration": 40
        },
        {
          "id": "emo_035",
          "type": "multiple_choice",
          "text": "Er hat großen Stress. ___",
          "sound": "emo_035.mp3",
          "soundText": "Er hat großen Stress. ___",
          "options": [
            "Trotzdem macht er jeden Tag Sport.",
            "Weil macht er jeden Tag Sport.",
            "Obwohl macht er jeden Tag Sport.",
            "Sondern macht er jeden Tag Sport."
          ],
          "answer": 0,
          "duration": 40
        },
        {
          "id": "emo_036",
          "type": "multiple_choice",
          "text": "Sie ist aufgeregt, ___",
          "sound": "emo_036.mp3",
          "soundText": "Sie ist aufgeregt, ___",
          "options": [
            "sondern morgen ihre Reise beginnt.",
            "trotzdem morgen ihre Reise beginnt.",
            "weil morgen ihre Reise beginnt.",
            "aber morgen ihre Reise beginnt."
          ],
          "answer": 2,
          "duration": 40
        },
        {
          "id": "emo_037",
          "type": "multiple_choice",
          "text": "Er schläft tief, ___",
          "sound": "emo_037.mp3",
          "soundText": "Er schläft tief, ___",
          "options": [
            "obwohl die Musik sehr laut ist.",
            "weil die Musik sehr laut ist.",
            "aber die Musik sehr laut ist.",
            "sondern die Musik sehr laut ist."
          ],
          "answer": 0,
          "duration": 40
        },
        {
          "id": "emo_038",
          "type": "multiple_choice",
          "text": "Ich bin überrascht, ___",
          "sound": "emo_038.mp3",
          "soundText": "Ich bin überrascht, ___",
          "options": [
            "weil ich freue mich nicht darüber.",
            "sondern ich freue mich nicht darüber.",
            "aber ich freue mich nicht darüber.",
            "obwohl ich freue mich nicht darüber."
          ],
          "answer": 2,
          "duration": 40
        },
        {
          "id": "emo_039",
          "type": "multiple_choice",
          "text": "Sie ist nicht wütend auf dich, ___",
          "sound": "emo_039.mp3",
          "soundText": "Sie ist nicht wütend auf dich, ___",
          "options": [
            "sondern enttäuscht.",
            "aber enttäuscht.",
            "weil enttäuscht.",
            "obwohl enttäuscht."
          ],
          "answer": 0,
          "duration": 40
        },
        {
          "id": "emo_040",
          "type": "multiple_choice",
          "text": "Er fühlt sich schuldig, ___",
          "sound": "emo_040.mp3",
          "soundText": "Er fühlt sich schuldig, ___",
          "options": [
            "aber er einen Fehler gemacht hat.",
            "obwohl er nichts falsch gemacht hat.",
            "sondern er einen Fehler gemacht hat.",
            "weil er einen Fehler gemacht hat."
          ],
          "answer": 3,
          "duration": 40
        }
      ]
    },
    {
      "id": "grammatik_b1",
      "name": "Grammatik B1",
      "icon": "📝",
      "questions": [
        {
          "id": "b1_001",
          "type": "multiple_choice",
          "text": "Der Hund _____ nicht ins Museum. – Modalverb im Präteritum?",
          "options": [
            "darf",
            "durfte",
            "dürfte",
            "gedurft"
          ],
          "answer": 1,
          "duration": 20
        },
        {
          "id": "b1_002",
          "type": "multiple_choice",
          "text": "Die Haustiere _____ draußen warten. – Modalverb im Präteritum (müssen)?",
          "options": [
            "müssen",
            "müssten",
            "mussten",
            "gemusst"
          ],
          "answer": 2,
          "duration": 20
        },
        {
          "id": "b1_003",
          "type": "multiple_choice",
          "text": "Wir _____ schon immer das Museum besuchen. – Modalverb im Präteritum (wollen)?",
          "options": [
            "wollen",
            "wollten",
            "wollte",
            "gewollt"
          ],
          "answer": 1,
          "duration": 20
        },
        {
          "id": "b1_004",
          "type": "multiple_choice",
          "text": "_____ hast du Interesse? – Fragepronomen für Interessen (Woran)?",
          "options": [
            "Worüber",
            "Woran",
            "Wofür",
            "Womit"
          ],
          "answer": 1,
          "duration": 15
        },
        {
          "id": "b1_005",
          "type": "multiple_choice",
          "text": "Ich mag keine Horrorfilme, _____ Komödien. – Konjunktion für positiven Gegensatz?",
          "options": [
            "aber",
            "denn",
            "obwohl",
            "sondern"
          ],
          "answer": 3,
          "duration": 20
        },
        {
          "id": "b1_006",
          "type": "multiple_choice",
          "text": "Wo ist die Fernbedienung? – Sie _____ auf dem Tisch. (Zustand/Position)",
          "options": [
            "legt",
            "liegt",
            "legte",
            "legen"
          ],
          "answer": 1,
          "duration": 20
        },
        {
          "id": "b1_007",
          "type": "multiple_choice",
          "text": "Wohin hast du die Fernbedienung _____? – Perfekt von legen?",
          "options": [
            "gelegen",
            "legen",
            "gelegt",
            "liegt"
          ],
          "answer": 2,
          "duration": 20
        },
        {
          "id": "b1_008",
          "type": "multiple_choice",
          "text": "Das Buch _____ im Regal. – Welches Verb zeigt eine stabile Position?",
          "options": [
            "stellt",
            "gestellt",
            "steht",
            "stellen"
          ],
          "answer": 2,
          "duration": 20
        },
        {
          "id": "b1_009",
          "type": "multiple_choice",
          "text": "Die Eltern schicken Mert ins Ausland, _____ er sein Studium beendet. – Finalsatz?",
          "options": [
            "weil",
            "obwohl",
            "als",
            "damit"
          ],
          "answer": 3,
          "duration": 20
        },
        {
          "id": "b1_010",
          "type": "multiple_choice",
          "text": "Mert ist im Ausland, _____ sein Studium zu beenden. – Infinitivkonstruktion?",
          "options": [
            "damit",
            "ohne",
            "um",
            "statt"
          ],
          "answer": 2,
          "duration": 20
        },
        {
          "id": "b1_011",
          "type": "multiple_choice",
          "text": "Er trinkt gern _____ Kaffee. – Adjektivendung: Nullartikel, Mask., Akkusativ?",
          "options": [
            "kalter",
            "kalte",
            "kaltens",
            "kalten"
          ],
          "answer": 3,
          "duration": 25
        },
        {
          "id": "b1_012",
          "type": "multiple_choice",
          "text": "Sie kauft _____ Brot. – Adjektivendung: Nullartikel, Neutrum, Akkusativ?",
          "options": [
            "frische",
            "frischer",
            "frisches",
            "frischem"
          ],
          "answer": 2,
          "duration": 25
        },
        {
          "id": "b1_013",
          "type": "multiple_choice",
          "text": "Welches Wort leitet eine indirekte Ja/Nein-Frage ein?",
          "options": [
            "dass",
            "als",
            "ob",
            "weil"
          ],
          "answer": 2,
          "duration": 15
        },
        {
          "id": "b1_014",
          "type": "multiple_choice",
          "text": "Ela fragt: Wie kalt ist es? -> Indirekt: Ela fragt, wie kalt es _____.",
          "options": [
            "sei",
            "ist",
            "war",
            "wäre"
          ],
          "answer": 1,
          "duration": 20
        },
        {
          "id": "b1_015",
          "type": "multiple_choice",
          "text": "Was ist die Nomenform von pünktlich?",
          "options": [
            "die Pünktliche",
            "das Pünktlich",
            "die Pünktlichkeit",
            "der Pünktlich"
          ],
          "answer": 2,
          "duration": 20
        },
        {
          "id": "b1_016",
          "type": "multiple_choice",
          "text": "Was ist die Nomenform von frei?",
          "options": [
            "die Freiheit",
            "das Freie",
            "die Freilichkeit",
            "der Frei"
          ],
          "answer": 0,
          "duration": 20
        },
        {
          "id": "b1_017",
          "type": "multiple_choice",
          "text": "Was ist die Nomenform von freundlich?",
          "options": [
            "die Freundschaft",
            "die Freundlichkeit",
            "das Freundliche",
            "der Freundlich"
          ],
          "answer": 1,
          "duration": 20
        },
        {
          "id": "b1_018",
          "type": "multiple_choice",
          "text": "_____ ich jung war, kam ich zum ersten Mal nach Berlin. – Temporalkonjunktion (einmalig)?",
          "options": [
            "Wenn",
            "Während",
            "Nachdem",
            "Als"
          ],
          "answer": 3,
          "duration": 20
        },
        {
          "id": "b1_019",
          "type": "multiple_choice",
          "text": "Was ist das Präteritum von kommen?",
          "options": [
            "kommte",
            "gekommen",
            "kam",
            "kommt"
          ],
          "answer": 2,
          "duration": 15
        },
        {
          "id": "b1_020",
          "type": "multiple_choice",
          "text": "Was ist das Präteritum von gehen?",
          "options": [
            "gehte",
            "gegangen",
            "geht",
            "ging"
          ],
          "answer": 3,
          "duration": 15
        },
        {
          "id": "b1_021",
          "type": "multiple_choice",
          "text": "Was ist das Präteritum von machen? (regelmäßiges Verb)",
          "options": [
            "mochte",
            "macht",
            "gemacht",
            "machte"
          ],
          "answer": 3,
          "duration": 15
        },
        {
          "id": "b1_022",
          "type": "multiple_choice",
          "text": "Ich gehe selten ins Kino, _____ ich großes Interesse an Filmen habe. – Konzessivsatz?",
          "options": [
            "deshalb",
            "trotzdem",
            "weil",
            "obwohl"
          ],
          "answer": 3,
          "duration": 20
        },
        {
          "id": "b1_023",
          "type": "multiple_choice",
          "text": "Ich habe großes Interesse an Filmen, _____ gehe ich selten ins Kino. – Konzessivadverb?",
          "options": [
            "obwohl",
            "weil",
            "trotzdem",
            "damit"
          ],
          "answer": 2,
          "duration": 20
        },
        {
          "id": "b1_024",
          "type": "multiple_choice",
          "text": "Welches Ausrufewort drückt Freude aus?",
          "options": [
            "Iiih!",
            "Autsch!",
            "Hurra!",
            "Schade!"
          ],
          "answer": 2,
          "duration": 15
        },
        {
          "id": "b1_025",
          "type": "multiple_choice",
          "text": "Manuela springt _____ als Alina. – Komparativ von hoch?",
          "options": [
            "hochter",
            "höcher",
            "hocher",
            "höher"
          ],
          "answer": 3,
          "duration": 20
        },
        {
          "id": "b1_026",
          "type": "multiple_choice",
          "text": "Wolfgang singt am _____. – Superlativ von tief (Adverb)?",
          "options": [
            "tiefste",
            "tiefster",
            "tiefsten",
            "tiefer"
          ],
          "answer": 2,
          "duration": 20
        },
        {
          "id": "b1_027",
          "type": "multiple_choice",
          "text": "Er hat die _____ Stimme. – Superlativ von tief als Adjektiv (bestimmter Artikel, fem.)?",
          "options": [
            "tiefste",
            "tiefsten",
            "tiefster",
            "tiefer"
          ],
          "answer": 0,
          "duration": 20
        },
        {
          "id": "b1_028",
          "type": "multiple_choice",
          "text": "Ich möchte gewinnen, _____ trainiere ich jeden Tag. – Konsequenzadverb?",
          "options": [
            "obwohl",
            "deshalb",
            "damit",
            "weil"
          ],
          "answer": 1,
          "duration": 20
        },
        {
          "id": "b1_029",
          "type": "multiple_choice",
          "text": "Ich habe vor, das Projekt durch_____führen. – Trennbares Verb mit zu?",
          "options": [
            "zu durchführen",
            "durchführen zu",
            "durchzuführen",
            "durchführen"
          ],
          "answer": 2,
          "duration": 20
        },
        {
          "id": "b1_030",
          "type": "multiple_choice",
          "text": "Sie soll nichts tun, _____ den Arzt vorher zu fragen. – ohne + zu?",
          "options": [
            "um",
            "damit",
            "ohne",
            "statt"
          ],
          "answer": 2,
          "duration": 20
        },
        {
          "id": "b1_031",
          "type": "multiple_choice",
          "text": "Sie müssen schreiben, _____ nur zu reden. – (an)statt + zu?",
          "options": [
            "ohne",
            "(an)statt",
            "um",
            "damit"
          ],
          "answer": 1,
          "duration": 20
        },
        {
          "id": "b1_032",
          "type": "multiple_choice",
          "text": "Wenn ich Zeit _____, würde ich ins Konzert gehen. – Konjunktiv II von haben?",
          "options": [
            "habe",
            "hatte",
            "gehabt",
            "hätte"
          ],
          "answer": 3,
          "duration": 20
        },
        {
          "id": "b1_033",
          "type": "multiple_choice",
          "text": "Ich wünschte, ich _____ so berühmt. – Konjunktiv II von sein?",
          "options": [
            "bin",
            "war",
            "sei",
            "wäre"
          ],
          "answer": 3,
          "duration": 20
        },
        {
          "id": "b1_034",
          "type": "multiple_choice",
          "text": "Wenn ich Zeit hätte, _____ ich ins Konzert gehen. – würde + Infinitiv?",
          "options": [
            "werde",
            "würde",
            "will",
            "wollte"
          ],
          "answer": 1,
          "duration": 20
        },
        {
          "id": "b1_035",
          "type": "multiple_choice",
          "text": "Aktiv: Man soll mehr Energie sparen. – Welche Passivform ist korrekt?",
          "options": [
            "Mehr Energie soll sparen werden.",
            "Mehr Energie soll gespart werden.",
            "Mehr Energie wird gesparen.",
            "Mehr Energie soll werden gespart."
          ],
          "answer": 1,
          "duration": 25
        },
        {
          "id": "b1_036",
          "type": "multiple_choice",
          "text": "Ich bin _____ diesem Projekt interessiert. – Welche Präposition?",
          "options": [
            "für",
            "über",
            "an",
            "mit"
          ],
          "answer": 2,
          "duration": 20
        },
        {
          "id": "b1_037",
          "type": "multiple_choice",
          "text": "Ich bin _____ dem Ergebnis zufrieden. – Welche Präposition?",
          "options": [
            "an",
            "über",
            "bei",
            "mit"
          ],
          "answer": 3,
          "duration": 20
        },
        {
          "id": "b1_038",
          "type": "multiple_choice",
          "text": "Ich bin _____ die Werke erstaunt. – Welche Präposition?",
          "options": [
            "mit",
            "an",
            "über",
            "für"
          ],
          "answer": 2,
          "duration": 20
        },
        {
          "id": "b1_039",
          "type": "multiple_choice",
          "text": "Das ist die Erfindung _____ Computers. – Genitiv, Maskulinum?",
          "options": [
            "der",
            "dem",
            "des",
            "den"
          ],
          "answer": 2,
          "duration": 20
        },
        {
          "id": "b1_040",
          "type": "multiple_choice",
          "text": "Das ist das Buch _____ Schriftstellerin. – Genitiv, Femininum?",
          "options": [
            "des",
            "die",
            "dem",
            "der"
          ],
          "answer": 3,
          "duration": 20
        },
        {
          "id": "b1_041",
          "type": "multiple_choice",
          "text": "Das ist der Film, _____ ich sehr interessant finde. – Relativpronomen (Mask., Akkusativ)?",
          "options": [
            "der",
            "dem",
            "dessen",
            "den"
          ],
          "answer": 3,
          "duration": 20
        },
        {
          "id": "b1_042",
          "type": "multiple_choice",
          "text": "Ich mag Talkshows, zu _____ man interessante Gäste einlädt. – Relativpronomen (Plural, Dativ)?",
          "options": [
            "die",
            "denen",
            "deren",
            "derer"
          ],
          "answer": 1,
          "duration": 25
        },
        {
          "id": "b1_043",
          "type": "multiple_choice",
          "text": "Ich hatte an einem Sprachkurs _____. – Plusquamperfekt von teilnehmen?",
          "options": [
            "teilgenommen",
            "teilnehmen",
            "genommen",
            "teilgenommt"
          ],
          "answer": 0,
          "duration": 20
        },
        {
          "id": "b1_044",
          "type": "multiple_choice",
          "text": "_____ ich den Kurs beendete, konnte ich mich besser verständigen. – Vorzeitigkeit?",
          "options": [
            "Als",
            "Während",
            "Nachdem",
            "Bevor"
          ],
          "answer": 2,
          "duration": 20
        },
        {
          "id": "b1_045",
          "type": "multiple_choice",
          "text": "_____ ich in Japan war, war meine Schwester in Australien. – Gleichzeitigkeit?",
          "options": [
            "Nachdem",
            "Als",
            "Während",
            "Bevor"
          ],
          "answer": 2,
          "duration": 20
        },
        {
          "id": "b1_046",
          "type": "multiple_choice",
          "text": "Plusquamperfekt – Mit welchen Hilfsverben wird es gebildet?",
          "options": [
            "werden + Partizip II",
            "haben + Infinitiv",
            "hatte/war + Partizip II",
            "wird + Partizip II"
          ],
          "answer": 2,
          "duration": 20
        },
        {
          "id": "b1_047",
          "type": "multiple_choice",
          "text": "Ich lese gern _____ Bücher. – Adjektivendung: Nullartikel, Plural, Akkusativ?",
          "options": [
            "spannende",
            "spannendes",
            "spannender",
            "spannendem"
          ],
          "answer": 0,
          "duration": 25
        },
        {
          "id": "b1_048",
          "type": "multiple_choice",
          "text": "Welcher Satz ist grammatikalisch korrekt (Konjunktiv II)?",
          "options": [
            "Wenn ich reich bin, kaufe ich ein Auto.",
            "Wenn ich reich wäre, würde ich ein Auto kaufen.",
            "Wenn ich reich war, kaufte ich ein Auto.",
            "Wenn ich reich wäre, kaufe ich ein Auto."
          ],
          "answer": 1,
          "duration": 25
        },
        {
          "id": "b1_049",
          "type": "multiple_choice",
          "text": "Trotz _____ Regens gingen wir spazieren. – Genitiv-Präposition?",
          "options": [
            "dem",
            "den",
            "des",
            "der"
          ],
          "answer": 2,
          "duration": 20
        },
        {
          "id": "b1_050",
          "type": "multiple_choice",
          "text": "Ich kenne den Mann, _____ Frau Lehrerin ist. – Relativpronomen im Genitiv?",
          "options": [
            "den",
            "dem",
            "dessen",
            "deren"
          ],
          "answer": 2,
          "duration": 25
        },
        {
          "id": "b1_051",
          "type": "multiple_choice",
          "text": "Nachdem er die Hausaufgaben _____, ging er schlafen. – Plusquamperfekt (machen)?",
          "options": [
            "gemacht hatte",
            "gemacht hat",
            "machte",
            "machen"
          ],
          "answer": 0,
          "duration": 25
        },
        {
          "id": "b1_052",
          "type": "multiple_choice",
          "text": "Welches Verb passt: Er _____ schon weggegangen, als ich kam.",
          "options": [
            "hatte",
            "war",
            "ist",
            "wird"
          ],
          "answer": 1,
          "duration": 20
        },
        {
          "id": "b1_053",
          "type": "multiple_choice",
          "text": "Klaus fragt: „Wann fängt der Kurs an?“ → Klaus will wissen, _____ der Kurs anfängt.",
          "options": [
            "ob",
            "wann",
            "dass",
            "wie"
          ],
          "answer": 1,
          "duration": 20
        },
        {
          "id": "b1_054",
          "type": "multiple_choice",
          "text": "Das war _____ peinlich! (Derecelendirme: çok/oldukça)",
          "options": [
            "gar nicht",
            "ein bisschen",
            "ziemlich",
            "nichts"
          ],
          "answer": 2,
          "duration": 15
        },
        {
          "id": "b1_055",
          "type": "multiple_choice",
          "text": "Ich bin froh _____ das gute Ergebnis. – Präposition?",
          "options": [
            "an",
            "über",
            "mit",
            "für"
          ],
          "answer": 1,
          "duration": 20
        },
        {
          "id": "b1_056",
          "type": "multiple_choice",
          "text": "_____ du mir bitte helfen? – Höfliche Bitte (Konjunktiv II)?",
          "options": [
            "Kannst",
            "Könntest",
            "Konntest",
            "Gekonnt"
          ],
          "answer": 1,
          "duration": 20
        },
        {
          "id": "b1_057",
          "type": "multiple_choice",
          "text": "Das Problem kann gelöst _____. – Passiv mit Modalverb?",
          "options": [
            "sein",
            "werden",
            "worden",
            "ist"
          ],
          "answer": 1,
          "duration": 20
        },
        {
          "id": "b1_058",
          "type": "multiple_choice",
          "text": "Es ist wichtig, jeden Tag Deutsch _____ lernen.",
          "options": [
            "zu",
            "um",
            "für",
            "statt"
          ],
          "answer": 0,
          "duration": 15
        },
        {
          "id": "b1_059",
          "type": "multiple_choice",
          "text": "Plusquamperfekt: Welches Hilfsverb passt zu „einschlafen“?",
          "options": [
            "hatte",
            "war",
            "ist",
            "bin"
          ],
          "answer": 1,
          "duration": 20
        },
        {
          "id": "b1_060",
          "type": "multiple_choice",
          "text": "Welche Konjunktion leitet einen Grund ein?",
          "options": [
            "obwohl",
            "deshalb",
            "weil",
            "trotzdem"
          ],
          "answer": 2,
          "duration": 15
        }
      ]
    }
  ]
}